{
    "key": "group_67a4b22e6af49",
    "title": "Шапка",
    "fields": [
        {
            "key": "field_67a4b22e7ce67",
            "label": "Меню слева",
            "name": "left_menu",
            "aria-label": "",
            "type": "flexible_content",
            "instructions": "",
            "required": 0,
            "conditional_logic": 0,
            "wrapper": {
                "width": "",
                "class": "",
                "id": ""
            },
            "layouts": {
                "layout_67a4b27e62311": {
                    "key": "layout_67a4b27e62311",
                    "name": "dress-category",
                    "label": "Категория платьев",
                    "display": "block",
                    "sub_fields": [
                        {
                            "key": "field_67a4b2ca53ecf",
                            "label": "Категория",
                            "name": "category",
                            "aria-label": "",
                            "type": "taxonomy",
                            "instructions": "",
                            "required": 0,
                            "conditional_logic": 0,
                            "wrapper": {
                                "width": "",
                                "class": "",
                                "id": ""
                            },
                            "taxonomy": "dress_category",
                            "add_term": 0,
                            "save_terms": 0,
                            "load_terms": 0,
                            "return_format": "id",
                            "field_type": "select",
                            "allow_null": 1,
                            "allow_in_bindings": 0,
                            "bidirectional": 0,
                            "multiple": 0,
                            "bidirectional_target": []
                        },
                        {
                            "key": "field_67a4b35253ed0",
                            "label": "Зеленый бейджик",
                            "name": "green_badge",
                            "aria-label": "",
                            "type": "text",
                            "instructions": "Если написать текст в этом поле, он будет добавлен в зеленый бейдж рядом с ссылкой.",
                            "required": 0,
                            "conditional_logic": 0,
                            "wrapper": {
                                "width": "",
                                "class": "",
                                "id": ""
                            },
                            "default_value": "",
                            "maxlength": 7,
                            "allow_in_bindings": 0,
                            "placeholder": "-30%",
                            "prepend": "",
                            "append": ""
                        },
                        {
                            "key": "field_67a4b5ef53ed1",
                            "label": "Столбцы в выпадающем меню",
                            "name": "dropdown_menu_columns",
                            "aria-label": "",
                            "type": "checkbox",
                            "instructions": "",
                            "required": 0,
                            "conditional_logic": 0,
                            "wrapper": {
                                "width": "",
                                "class": "",
                                "id": ""
                            },
                            "choices": {
                                "silhouette": "Силуэт",
                                "style": "Стиль",
                                "fabric": "Ткань",
                                "brand": "Топ бренды",
                                "price": "Стоимость"
                            },
                            "default_value": [
                                "silhouette",
                                "style",
                                "fabric",
                                "brand",
                                "price"
                            ],
                            "return_format": "value",
                            "allow_custom": 0,
                            "allow_in_bindings": 1,
                            "layout": "vertical",
                            "toggle": 0,
                            "save_custom": 0,
                            "custom_choice_button_text": "Добавить новый выбор"
                        },
                        {
                            "key": "field_67a4b71a53ed2",
                            "label": "Ссылки стоимости",
                            "name": "price_links",
                            "aria-label": "",
                            "type": "repeater",
                            "instructions": "",
                            "required": 0,
                            "conditional_logic": [
                                [
                                    {
                                        "field": "field_67a4b5ef53ed1",
                                        "operator": "==",
                                        "value": "price"
                                    }
                                ]
                            ],
                            "wrapper": {
                                "width": "",
                                "class": "",
                                "id": ""
                            },
                            "layout": "table",
                            "min": 0,
                            "max": 0,
                            "collapsed": "",
                            "button_label": "Добавить",
                            "rows_per_page": 20,
                            "sub_fields": [
                                {
                                    "key": "field_67a4b76e53ed4",
                                    "label": "Минимальная цена",
                                    "name": "min_price",
                                    "aria-label": "",
                                    "type": "number",
                                    "instructions": "",
                                    "required": 0,
                                    "conditional_logic": 0,
                                    "wrapper": {
                                        "width": "",
                                        "class": "",
                                        "id": ""
                                    },
                                    "default_value": "",
                                    "min": 0,
                                    "max": 1000000,
                                    "allow_in_bindings": 0,
                                    "placeholder": "",
                                    "step": 1,
                                    "prepend": "",
                                    "append": "",
                                    "parent_repeater": "field_67a4b71a53ed2"
                                },
                                {
                                    "key": "field_67a4b7d253ed5",
                                    "label": "Максимальная цена",
                                    "name": "max_price",
                                    "aria-label": "",
                                    "type": "number",
                                    "instructions": "",
                                    "required": 0,
                                    "conditional_logic": 0,
                                    "wrapper": {
                                        "width": "",
                                        "class": "",
                                        "id": ""
                                    },
                                    "default_value": "",
                                    "min": 0,
                                    "max": 1000000,
                                    "allow_in_bindings": 0,
                                    "placeholder": "",
                                    "step": 1,
                                    "prepend": "",
                                    "append": "",
                                    "parent_repeater": "field_67a4b71a53ed2"
                                }
                            ]
                        }
                    ],
                    "min": "",
                    "max": ""
                },
                "layout_67a5c5a027d63": {
                    "key": "layout_67a5c5a027d63",
                    "name": "simple-link",
                    "label": "Обычная ссылка",
                    "display": "block",
                    "sub_fields": [
                        {
                            "key": "field_67a5c5b727d66",
                            "label": "Ссылка",
                            "name": "link",
                            "aria-label": "",
                            "type": "link",
                            "instructions": "",
                            "required": 0,
                            "conditional_logic": 0,
                            "wrapper": {
                                "width": "",
                                "class": "",
                                "id": ""
                            },
                            "return_format": "",
                            "allow_in_bindings": 0
                        },
                        {
                            "key": "field_67a5c5c827d67",
                            "label": "Зеленый бейджик",
                            "name": "green_badge",
                            "aria-label": "",
                            "type": "text",
                            "instructions": "Если написать текст в этом поле, он будет добавлен в зеленый бейдж рядом с ссылкой.",
                            "required": 0,
                            "conditional_logic": 0,
                            "wrapper": {
                                "width": "",
                                "class": "",
                                "id": ""
                            },
                            "default_value": "",
                            "maxlength": 7,
                            "allow_in_bindings": 0,
                            "placeholder": "-30%",
                            "prepend": "",
                            "append": ""
                        }
                    ],
                    "min": "",
                    "max": ""
                }
            },
            "min": "",
            "max": 5,
            "button_label": "Добавить"
        },
        {
            "key": "field_67a5c62927d68",
            "label": "Меню справа",
            "name": "right_menu",
            "aria-label": "",
            "type": "flexible_content",
            "instructions": "",
            "required": 0,
            "conditional_logic": 0,
            "wrapper": {
                "width": "",
                "class": "",
                "id": ""
            },
            "layouts": {
                "layout_67a4b27e62311": {
                    "key": "layout_67a4b27e62311",
                    "name": "dress-category",
                    "label": "Категория платьев",
                    "display": "block",
                    "sub_fields": [
                        {
                            "key": "field_67a5c62927d6a",
                            "label": "Категория",
                            "name": "category",
                            "aria-label": "",
                            "type": "taxonomy",
                            "instructions": "",
                            "required": 0,
                            "conditional_logic": 0,
                            "wrapper": {
                                "width": "",
                                "class": "",
                                "id": ""
                            },
                            "taxonomy": "dress_category",
                            "add_term": 0,
                            "save_terms": 0,
                            "load_terms": 0,
                            "return_format": "id",
                            "field_type": "select",
                            "allow_null": 1,
                            "allow_in_bindings": 0,
                            "bidirectional": 0,
                            "multiple": 0,
                            "bidirectional_target": []
                        },
                        {
                            "key": "field_67a5c62927d6b",
                            "label": "Зеленый бейджик",
                            "name": "green_badge",
                            "aria-label": "",
                            "type": "text",
                            "instructions": "Если написать текст в этом поле, он будет добавлен в зеленый бейдж рядом с ссылкой.",
                            "required": 0,
                            "conditional_logic": 0,
                            "wrapper": {
                                "width": "",
                                "class": "",
                                "id": ""
                            },
                            "default_value": "",
                            "maxlength": 7,
                            "allow_in_bindings": 0,
                            "placeholder": "-30%",
                            "prepend": "",
                            "append": ""
                        },
                        {
                            "key": "field_67a5c62927d6c",
                            "label": "Столбцы в выпадающем меню",
                            "name": "dropdown_menu_columns",
                            "aria-label": "",
                            "type": "select",
                            "instructions": "",
                            "required": 0,
                            "conditional_logic": 0,
                            "wrapper": {
                                "width": "",
                                "class": "",
                                "id": ""
                            },
                            "choices": {
                                "silhouette": "Силуэт",
                                "style": "Стиль",
                                "fabric": "Ткань",
                                "brand": "Топ бренды",
                                "price": "Стоимость"
                            },
                            "default_value": [
                                "silhouette",
                                "style",
                                "fabric",
                                "brand",
                                "price"
                            ],
                            "return_format": "value",
                            "multiple": 1,
                            "allow_null": 0,
                            "allow_in_bindings": 0,
                            "ui": 0,
                            "ajax": 0,
                            "placeholder": ""
                        },
                        {
                            "key": "field_67a5c62927d6d",
                            "label": "Ссылки стоимости",
                            "name": "price_links",
                            "aria-label": "",
                            "type": "repeater",
                            "instructions": "",
                            "required": 0,
                            "conditional_logic": [
                                [
                                    {
                                        "field": "field_67a5c62927d6c",
                                        "operator": "==contains",
                                        "value": "price"
                                    }
                                ]
                            ],
                            "wrapper": {
                                "width": "",
                                "class": "",
                                "id": ""
                            },
                            "layout": "table",
                            "min": 0,
                            "max": 0,
                            "collapsed": "",
                            "button_label": "Добавить",
                            "rows_per_page": 20,
                            "sub_fields": [
                                {
                                    "key": "field_67a5c62927d6e",
                                    "label": "Минимальная цена",
                                    "name": "min_price",
                                    "aria-label": "",
                                    "type": "number",
                                    "instructions": "",
                                    "required": 0,
                                    "conditional_logic": 0,
                                    "wrapper": {
                                        "width": "",
                                        "class": "",
                                        "id": ""
                                    },
                                    "default_value": "",
                                    "min": 0,
                                    "max": 1000000,
                                    "allow_in_bindings": 0,
                                    "placeholder": "",
                                    "step": 1,
                                    "prepend": "",
                                    "append": "",
                                    "parent_repeater": "field_67a5c62927d6d"
                                },
                                {
                                    "key": "field_67a5c62927d6f",
                                    "label": "Максимальная цена",
                                    "name": "max_price",
                                    "aria-label": "",
                                    "type": "number",
                                    "instructions": "",
                                    "required": 0,
                                    "conditional_logic": 0,
                                    "wrapper": {
                                        "width": "",
                                        "class": "",
                                        "id": ""
                                    },
                                    "default_value": "",
                                    "min": 0,
                                    "max": 1000000,
                                    "allow_in_bindings": 0,
                                    "placeholder": "",
                                    "step": 1,
                                    "prepend": "",
                                    "append": "",
                                    "parent_repeater": "field_67a5c62927d6d"
                                }
                            ]
                        }
                    ],
                    "min": "",
                    "max": ""
                },
                "layout_67a5c5a027d63": {
                    "key": "layout_67a5c5a027d63",
                    "name": "simple-link",
                    "label": "Обычная ссылка",
                    "display": "block",
                    "sub_fields": [
                        {
                            "key": "field_67a5c62927d70",
                            "label": "Ссылка",
                            "name": "link",
                            "aria-label": "",
                            "type": "link",
                            "instructions": "",
                            "required": 0,
                            "conditional_logic": 0,
                            "wrapper": {
                                "width": "",
                                "class": "",
                                "id": ""
                            },
                            "return_format": "array",
                            "allow_in_bindings": 0
                        },
                        {
                            "key": "field_67a5c62927d71",
                            "label": "Зеленый бейджик",
                            "name": "green_badge",
                            "aria-label": "",
                            "type": "text",
                            "instructions": "Если написать текст в этом поле, он будет добавлен в зеленый бейдж рядом с ссылкой.",
                            "required": 0,
                            "conditional_logic": 0,
                            "wrapper": {
                                "width": "",
                                "class": "",
                                "id": ""
                            },
                            "default_value": "",
                            "maxlength": 7,
                            "allow_in_bindings": 0,
                            "placeholder": "-30%",
                            "prepend": "",
                            "append": ""
                        }
                    ],
                    "min": "",
                    "max": ""
                }
            },
            "min": "",
            "max": 4,
            "button_label": "Добавить"
        }
    ],
    "location": [
        [
            {
                "param": "options_page",
                "operator": "==",
                "value": "website-header-options"
            }
        ]
    ],
    "menu_order": 0,
    "position": "normal",
    "style": "default",
    "label_placement": "top",
    "instruction_placement": "label",
    "hide_on_screen": "",
    "active": true,
    "description": "",
    "show_in_rest": 0,
    "modified": 1738919296
}
